{"captain": {"href": "https://crest-tq.eveonline.com/characters/669236277/", "name": "GROUND XERO", "icon": {"href": "http://imageserver.eveonline.com/Character/669236277_128.jpg"}}, "name": "Project.Mayhem.", "iskKilled": 4394847479, "iskKilled_str": "4394847479", "shipsKilled_str": "23", "banFrequency": [{"numBans": 1, "shipType": {"href": "https://crest-tq.eveonline.com/inventory/types/33820/", "name": "Barghest", "icon": {"href": "http://imageserver.eveonline.com/Type/33820_64.png"}}, "numBans_str": "1"}, {"numBans": 1, "shipType": {"href": "https://crest-tq.eveonline.com/inventory/types/33818/", "name": "Orthrus", "icon": {"href": "http://imageserver.eveonline.com/Type/33818_64.png"}}, "numBans_str": "1"}, {"numBans": 1, "shipType": {"href": "https://crest-tq.eveonline.com/inventory/types/29988/", "name": "Proteus", "icon": {"href": "http://imageserver.eveonline.com/Type/29988_64.png"}}, "numBans_str": "1"}, {"numBans": 1, "shipType": {"href": "https://crest-tq.eveonline.com/inventory/types/29984/", "name": "Tengu", "icon": {"href": "http://imageserver.eveonline.com/Type/29984_64.png"}}, "numBans_str": "1"}, {"numBans": 1, "shipType": {"href": "https://crest-tq.eveonline.com/inventory/types/22444/", "name": "Sleipnir", "icon": {"href": "http://imageserver.eveonline.com/Type/22444_64.png"}}, "numBans_str": "1"}, {"numBans": 1, "shipType": {"href": "https://crest-tq.eveonline.com/inventory/types/22436/", "name": "Widow", "icon": {"href": "http://imageserver.eveonline.com/Type/22436_64.png"}}, "numBans_str": "1"}, {"numBans": 1, "shipType": {"href": "https://crest-tq.eveonline.com/inventory/types/12038/", "name": "Purifier", "icon": {"href": "http://imageserver.eveonline.com/Type/12038_64.png"}}, "numBans_str": "1"}, {"numBans": 1, "shipType": {"href": "https://crest-tq.eveonline.com/inventory/types/11989/", "name": "Oneiros", "icon": {"href": "http://imageserver.eveonline.com/Type/11989_64.png"}}, "numBans_str": "1"}, {"numBans": 1, "shipType": {"href": "https://crest-tq.eveonline.com/inventory/types/11987/", "name": "Guardian", "icon": {"href": "http://imageserver.eveonline.com/Type/11987_64.png"}}, "numBans_str": "1"}, {"numBans": 1, "shipType": {"href": "https://crest-tq.eveonline.com/inventory/types/632/", "name": "Blackbird", "icon": {"href": "http://imageserver.eveonline.com/Type/632_64.png"}}, "numBans_str": "1"}], "members": {"href": "https://crest-tq.eveonline.com/tournaments/teams/166/members/"}, "pilots": [{"href": "https://crest-tq.eveonline.com/characters/1832436128/", "name": "Tau AD", "icon": {"href": "http://imageserver.eveonline.com/Character/1832436128_128.jpg"}}, {"href": "https://crest-tq.eveonline.com/characters/803914370/", "name": "Kassi", "icon": {"href": "http://imageserver.eveonline.com/Character/803914370_128.jpg"}}, {"href": "https://crest-tq.eveonline.com/characters/542316057/", "name": "JSkywalker", "icon": {"href": "http://imageserver.eveonline.com/Character/542316057_128.jpg"}}, {"href": "https://crest-tq.eveonline.com/characters/1687992232/", "name": "Honen", "icon": {"href": "http://imageserver.eveonline.com/Character/1687992232_128.jpg"}}, {"href": "https://crest-tq.eveonline.com/characters/1245725705/", "name": "Battletroll484", "icon": {"href": "http://imageserver.eveonline.com/Character/1245725705_128.jpg"}}, {"href": "https://crest-tq.eveonline.com/characters/871136074/", "name": "Hainesy", "icon": {"href": "http://imageserver.eveonline.com/Character/871136074_128.jpg"}}, {"href": "https://crest-tq.eveonline.com/characters/90526637/", "name": "Alex Champ", "icon": {"href": "http://imageserver.eveonline.com/Character/90526637_128.jpg"}}, {"href": "https://crest-tq.eveonline.com/characters/1441996590/", "name": "IndianLord", "icon": {"href": "http://imageserver.eveonline.com/Character/1441996590_128.jpg"}}, {"href": "https://crest-tq.eveonline.com/characters/194270128/", "name": "Devils Fighter", "icon": {"href": "http://imageserver.eveonline.com/Character/194270128_128.jpg"}}, {"href": "https://crest-tq.eveonline.com/characters/90929265/", "name": "Tema Piterskiy", "icon": {"href": "http://imageserver.eveonline.com/Character/90929265_128.jpg"}}, {"href": "https://crest-tq.eveonline.com/characters/389802894/", "name": "Franz Tek", "icon": {"href": "http://imageserver.eveonline.com/Character/389802894_128.jpg"}}, {"href": "https://crest-tq.eveonline.com/characters/91593526/", "name": "Kijper Sky", "icon": {"href": "http://imageserver.eveonline.com/Character/91593526_128.jpg"}}, {"href": "https://crest-tq.eveonline.com/characters/931138935/", "name": "Teh Tripple", "icon": {"href": "http://imageserver.eveonline.com/Character/931138935_128.jpg"}}, {"href": "https://crest-tq.eveonline.com/characters/1179201785/", "name": "Huan Matus", "icon": {"href": "http://imageserver.eveonline.com/Character/1179201785_128.jpg"}}, {"href": "https://crest-tq.eveonline.com/characters/707244667/", "name": "G Genetic", "icon": {"href": "http://imageserver.eveonline.com/Character/707244667_128.jpg"}}, {"href": "https://crest-tq.eveonline.com/characters/1370149666/", "name": "Kaleesa", "icon": {"href": "http://imageserver.eveonline.com/Character/1370149666_128.jpg"}}, {"href": "https://crest-tq.eveonline.com/characters/91017278/", "name": "Ivy Kuznetsova", "icon": {"href": "http://imageserver.eveonline.com/Character/91017278_128.jpg"}}, {"href": "https://crest-tq.eveonline.com/characters/669236277/", "name": "GROUND XERO", "icon": {"href": "http://imageserver.eveonline.com/Character/669236277_128.jpg"}}], "banFrequencyAgainst": [{"numBans": 1, "shipType": {"href": "https://crest-tq.eveonline.com/inventory/types/33820/", "name": "Barghest", "icon": {"href": "http://imageserver.eveonline.com/Type/33820_64.png"}}, "numBans_str": "1"}, {"numBans": 1, "shipType": {"href": "https://crest-tq.eveonline.com/inventory/types/32309/", "name": "Scorpion Navy Issue", "icon": {"href": "http://imageserver.eveonline.com/Type/32309_64.png"}}, "numBans_str": "1"}, {"numBans": 1, "shipType": {"href": "https://crest-tq.eveonline.com/inventory/types/29990/", "name": "Loki", "icon": {"href": "http://imageserver.eveonline.com/Type/29990_64.png"}}, "numBans_str": "1"}, {"numBans": 1, "shipType": {"href": "https://crest-tq.eveonline.com/inventory/types/29988/", "name": "Proteus", "icon": {"href": "http://imageserver.eveonline.com/Type/29988_64.png"}}, "numBans_str": "1"}, {"numBans": 1, "shipType": {"href": "https://crest-tq.eveonline.com/inventory/types/29986/", "name": "Legion", "icon": {"href": "http://imageserver.eveonline.com/Type/29986_64.png"}}, "numBans_str": "1"}, {"numBans": 1, "shipType": {"href": "https://crest-tq.eveonline.com/inventory/types/29984/", "name": "Tengu", "icon": {"href": "http://imageserver.eveonline.com/Type/29984_64.png"}}, "numBans_str": "1"}, {"numBans": 1, "shipType": {"href": "https://crest-tq.eveonline.com/inventory/types/17920/", "name": "Bhaalgorn", "icon": {"href": "http://imageserver.eveonline.com/Type/17920_64.png"}}, "numBans_str": "1"}, {"numBans": 1, "shipType": {"href": "https://crest-tq.eveonline.com/inventory/types/11989/", "name": "Oneiros", "icon": {"href": "http://imageserver.eveonline.com/Type/11989_64.png"}}, "numBans_str": "1"}, {"numBans": 1, "shipType": {"href": "https://crest-tq.eveonline.com/inventory/types/11987/", "name": "Guardian", "icon": {"href": "http://imageserver.eveonline.com/Type/11987_64.png"}}, "numBans_str": "1"}, {"numBans": 1, "shipType": {"href": "https://crest-tq.eveonline.com/inventory/types/643/", "name": "Armageddon", "icon": {"href": "http://imageserver.eveonline.com/Type/643_64.png"}}, "numBans_str": "1"}], "shipsKilled": 23}