{"captain": {"href": "https://crest-tq.eveonline.com/characters/1674115962/", "name": "joecuster", "icon": {"href": "http://imageserver.eveonline.com/Character/1674115962_128.jpg"}}, "name": "Psychotic Tendencies", "iskKilled": 158040388, "iskKilled_str": "158040388", "shipsKilled_str": "4", "banFrequency": [{"numBans": 2, "shipType": {"href": "https://crest-tq.eveonline.com/inventory/types/11989/", "name": "Oneiros", "icon": {"href": "http://imageserver.eveonline.com/Type/11989_64.png"}}, "numBans_str": "2"}, {"numBans": 1, "shipType": {"href": "https://crest-tq.eveonline.com/inventory/types/11987/", "name": "Guardian", "icon": {"href": "http://imageserver.eveonline.com/Type/11987_64.png"}}, "numBans_str": "1"}, {"numBans": 1, "shipType": {"href": "https://crest-tq.eveonline.com/inventory/types/643/", "name": "Armageddon", "icon": {"href": "http://imageserver.eveonline.com/Type/643_64.png"}}, "numBans_str": "1"}], "members": {"href": "https://crest-tq.eveonline.com/tournaments/teams/283/members/"}, "pilots": [{"href": "https://crest-tq.eveonline.com/characters/514613667/", "name": "Vrikaan Phoenix", "icon": {"href": "http://imageserver.eveonline.com/Character/514613667_128.jpg"}}, {"href": "https://crest-tq.eveonline.com/characters/91788612/", "name": "Titanic Nut", "icon": {"href": "http://imageserver.eveonline.com/Character/91788612_128.jpg"}}, {"href": "https://crest-tq.eveonline.com/characters/376769733/", "name": "Pickles TheDrummer", "icon": {"href": "http://imageserver.eveonline.com/Character/376769733_128.jpg"}}, {"href": "https://crest-tq.eveonline.com/characters/91282513/", "name": "Jayarr Altol", "icon": {"href": "http://imageserver.eveonline.com/Character/91282513_128.jpg"}}, {"href": "https://crest-tq.eveonline.com/characters/90781234/", "name": "Koenig Yazria", "icon": {"href": "http://imageserver.eveonline.com/Character/90781234_128.jpg"}}, {"href": "https://crest-tq.eveonline.com/characters/92378289/", "name": "Act-Mack PVT", "icon": {"href": "http://imageserver.eveonline.com/Character/92378289_128.jpg"}}, {"href": "https://crest-tq.eveonline.com/characters/95761970/", "name": "Imogen Ananke", "icon": {"href": "http://imageserver.eveonline.com/Character/95761970_128.jpg"}}, {"href": "https://crest-tq.eveonline.com/characters/1695969155/", "name": "Ivy Lash", "icon": {"href": "http://imageserver.eveonline.com/Character/1695969155_128.jpg"}}, {"href": "https://crest-tq.eveonline.com/characters/888715640/", "name": "MasterofDisaster BG", "icon": {"href": "http://imageserver.eveonline.com/Character/888715640_128.jpg"}}, {"href": "https://crest-tq.eveonline.com/characters/669448857/", "name": "Lich Reaper", "icon": {"href": "http://imageserver.eveonline.com/Character/669448857_128.jpg"}}, {"href": "https://crest-tq.eveonline.com/characters/1674115962/", "name": "joecuster", "icon": {"href": "http://imageserver.eveonline.com/Character/1674115962_128.jpg"}}, {"href": "https://crest-tq.eveonline.com/characters/973451643/", "name": "blabla4868", "icon": {"href": "http://imageserver.eveonline.com/Character/973451643_128.jpg"}}], "banFrequencyAgainst": [{"numBans": 1, "shipType": {"href": "https://crest-tq.eveonline.com/inventory/types/22466/", "name": "Astarte", "icon": {"href": "http://imageserver.eveonline.com/Type/22466_64.png"}}, "numBans_str": "1"}, {"numBans": 1, "shipType": {"href": "https://crest-tq.eveonline.com/inventory/types/17740/", "name": "Vindicator", "icon": {"href": "http://imageserver.eveonline.com/Type/17740_64.png"}}, "numBans_str": "1"}, {"numBans": 1, "shipType": {"href": "https://crest-tq.eveonline.com/inventory/types/11194/", "name": "Kitsune", "icon": {"href": "http://imageserver.eveonline.com/Type/11194_64.png"}}, "numBans_str": "1"}, {"numBans": 1, "shipType": {"href": "https://crest-tq.eveonline.com/inventory/types/632/", "name": "Blackbird", "icon": {"href": "http://imageserver.eveonline.com/Type/632_64.png"}}, "numBans_str": "1"}], "shipsKilled": 4}