{"captain": {"href": "https://crest-tq.eveonline.com/characters/990473787/", "name": "General Thunderbolt", "icon": {"href": "http://imageserver.eveonline.com/Character/990473787_128.jpg"}}, "name": "Epic Finns Winning Tournaments", "iskKilled": 3109502240, "iskKilled_str": "3109502240", "shipsKilled_str": "12", "banFrequency": [{"numBans": 2, "shipType": {"href": "https://crest-tq.eveonline.com/inventory/types/17843/", "name": "Vexor Navy Issue", "icon": {"href": "http://imageserver.eveonline.com/Type/17843_64.png"}}, "numBans_str": "2"}, {"numBans": 2, "shipType": {"href": "https://crest-tq.eveonline.com/inventory/types/12005/", "name": "Ishtar", "icon": {"href": "http://imageserver.eveonline.com/Type/12005_64.png"}}, "numBans_str": "2"}, {"numBans": 1, "shipType": {"href": "https://crest-tq.eveonline.com/inventory/types/17740/", "name": "Vindicator", "icon": {"href": "http://imageserver.eveonline.com/Type/17740_64.png"}}, "numBans_str": "1"}, {"numBans": 1, "shipType": {"href": "https://crest-tq.eveonline.com/inventory/types/645/", "name": "Dominix", "icon": {"href": "http://imageserver.eveonline.com/Type/645_64.png"}}, "numBans_str": "1"}], "members": {"href": "https://crest-tq.eveonline.com/tournaments/teams/85/members/"}, "pilots": [{"href": "https://crest-tq.eveonline.com/characters/463181537/", "name": "n3xxz", "icon": {"href": "http://imageserver.eveonline.com/Character/463181537_128.jpg"}}, {"href": "https://crest-tq.eveonline.com/characters/990473787/", "name": "General Thunderbolt", "icon": {"href": "http://imageserver.eveonline.com/Character/990473787_128.jpg"}}, {"href": "https://crest-tq.eveonline.com/characters/2084907174/", "name": "Bubblespoon", "icon": {"href": "http://imageserver.eveonline.com/Character/2084907174_128.jpg"}}, {"href": "https://crest-tq.eveonline.com/characters/336263433/", "name": "Malo Fakaki", "icon": {"href": "http://imageserver.eveonline.com/Character/336263433_128.jpg"}}, {"href": "https://crest-tq.eveonline.com/characters/1304117020/", "name": "Angel Wolf99", "icon": {"href": "http://imageserver.eveonline.com/Character/1304117020_128.jpg"}}, {"href": "https://crest-tq.eveonline.com/characters/1948886582/", "name": "Ugly Eric", "icon": {"href": "http://imageserver.eveonline.com/Character/1948886582_128.jpg"}}, {"href": "https://crest-tq.eveonline.com/characters/1079060537/", "name": "DeathOfficer", "icon": {"href": "http://imageserver.eveonline.com/Character/1079060537_128.jpg"}}, {"href": "https://crest-tq.eveonline.com/characters/951883866/", "name": "Deszra", "icon": {"href": "http://imageserver.eveonline.com/Character/951883866_128.jpg"}}, {"href": "https://crest-tq.eveonline.com/characters/1708653563/", "name": "Depili", "icon": {"href": "http://imageserver.eveonline.com/Character/1708653563_128.jpg"}}, {"href": "https://crest-tq.eveonline.com/characters/1893320284/", "name": "Mauno Materialisti", "icon": {"href": "http://imageserver.eveonline.com/Character/1893320284_128.jpg"}}], "banFrequencyAgainst": [{"numBans": 1, "shipType": {"href": "https://crest-tq.eveonline.com/inventory/types/28710/", "name": "Golem", "icon": {"href": "http://imageserver.eveonline.com/Type/28710_64.png"}}, "numBans_str": "1"}, {"numBans": 1, "shipType": {"href": "https://crest-tq.eveonline.com/inventory/types/28665/", "name": "Vargur", "icon": {"href": "http://imageserver.eveonline.com/Type/28665_64.png"}}, "numBans_str": "1"}, {"numBans": 1, "shipType": {"href": "https://crest-tq.eveonline.com/inventory/types/22444/", "name": "Sleipnir", "icon": {"href": "http://imageserver.eveonline.com/Type/22444_64.png"}}, "numBans_str": "1"}, {"numBans": 1, "shipType": {"href": "https://crest-tq.eveonline.com/inventory/types/11978/", "name": "Scimitar", "icon": {"href": "http://imageserver.eveonline.com/Type/11978_64.png"}}, "numBans_str": "1"}, {"numBans": 1, "shipType": {"href": "https://crest-tq.eveonline.com/inventory/types/643/", "name": "Armageddon", "icon": {"href": "http://imageserver.eveonline.com/Type/643_64.png"}}, "numBans_str": "1"}, {"numBans": 1, "shipType": {"href": "https://crest-tq.eveonline.com/inventory/types/633/", "name": "Celestis", "icon": {"href": "http://imageserver.eveonline.com/Type/633_64.png"}}, "numBans_str": "1"}], "shipsKilled": 12}